{
  "count": 1,
  "cards": [
    {
      "type": "COMPONENT_CARD",
      "props": {
        "id": "2:5578fd6b-830c-4a4f-a11b-46688d1685103",
        "meta": {
          "name": "PRODUCT_STORY",
          "app": {
            "id": 2,
            "name": "CoMS"
          },
          "tags": [
            "Style Guru",
            "men",
            "men's fashion",
            "featured",
            "rules to wearing socks",
            "style rules",
            "sock etiquettes",
            "Style Help"
          ]
        },
        "sequence": 103,
        "activities": {
          "clicks": {
            "count": 46
          },
          "likes": {
            "count": 1,
            "liked": true
          },
          "comments": {
            "count": 0
          },
          "shares": {
            "count": 0,
            "shared": true
          }
        }
      },
      "children": [
        {
          "type": "HEADER_CONTEXT",
          "props": {
            "title": [
              {
                "text": "Featured in "
              },
              {
                "text": "#DIY, ",
                "link": "/tags/diy"
              },
              {
                "text": "#Style",
                "link": "/tags/style"
              }
            ]
          }
        },
        {
          "type": "PRODUCT_RACK",
          "props": {
            "products": [
              {
                "stylename": "American Swan Men Brown Suede Casual Shoes",
                "brands_facet": "American Swan1",
                "price": "3999",
                "discount": "1600",
                "discounted_price": "2399",
                "discount_label": "40% OFF",
                "link": "/797080",
                "image": {
                  "src": "http://myntra.myntassets.com/image/style/properties/797080/American-Swan-Men-Casual-Shoes_1_691d38a71069cb01d3d976531564dede.jpg",
                  "width": 1080,
                  "height": 1440,
                  "provider": "MYNT_ASSETS"
                }
              },
              {
                "stylename": "American Swan Men Grey Suede Casual Shoes",
                "brands_facet": "American Swan2",
                "price": "3699",
                "discount": "1480",
                "discounted_price": "2219",
                "discount_label": "40% OFF",
                "link": "/797083",
                "image": {
                  "src": "http://myntra.myntassets.com/image/style/properties/797080/American-Swan-Men-Casual-Shoes_1_691d38a71069cb01d3d976531564dede.jpg",
                  "width": 1080,
                  "height": 1440,
                  "provider": "MYNT_ASSETS"
                }
              },
              {
                "stylename": "American Swan Beige Trousers",
                "brands_facet": "American Swan3",
                "price": "1599",
                "discount": "640",
                "discounted_price": "959",
                "discount_label": "40% OFF",
                "url": "/858669",
                "image": {
                  "src": "http://myntra.myntassets.com/image/style/properties/858669/American-Swan-Beige-Trousers_1_4f122c400cdd26ad16e2622669758027.jpg",
                  "width": 1080,
                  "height": 1440,
                  "provider": "MYNT_ASSETS"
                }
              }
            ]
          }
        },
        {
          "type": "DESCRIPTION_TEXT",
          "props": {
            "text": "VIDEO | 1:17"
          }
        },
        {
          "type": "TITLE_TEXT",
          "props": {
            "text": "5 uses of Vaseline you couldn’t have guessed"
          }
        },
        {
          "type": "FEEDBACK_VIEW_LIKE_COMMENT",
          "props": {}
        },
        {
          "type": "FOOTER_LIKE_SHARE",
          "props": {}
        }
      ]
    }
  ]
}
